[
  {
    "userEmail": "google-oauth2|113512357034311089175",
    "imageUrls": [
      {
        "imageUrl": "https://upload.wikimedia.org/wikipedia/en/thumb/c/c8/LookSharp.jpg/220px-LookSharp.jpg",
        "imageTitle": "Look Sharp! (Roxette album) - Wikipedia"
      },
      {
        "imageUrl": "https://cdn.britannica.com/18/136518-050-CD0E49C6/The-Beatles-Ringo-Starr-Paul-McCartney-George.jpg",
        "imageTitle": "Beatles | Members, Songs, Albums, & Facts | Britannica"
      }
    ]
  },
  {
    "userEmail": "github|144778840",
    "imageUrls": [
      {
        "imageUrl": "https://media.mutualart.com/Images//2022_11/19/16/160417731/4941ca30-ea4f-4cc2-8013-0785719def32.Jpeg",
        "imageTitle": "Julius Kronberg | Tomten med katterna i köket. (1872) | MutualArt"
      }
    ]
  }
]
